{"a":{"b":"robot","c":"2014-02-03 23:51:21.423238","e":"1","d":30},"f":{"g":[{"h":0,"i":"resources/gfx/characters/costumes_forgotten/ghost_disappear.png"}],"j":[{"h":0,"k":"body","l":0}],"m":[],"n":[]},"o":{"p":"Poof","q":[{"k":"Poof","r":9,"s":false,"t":[{"u":0,"v":0,"y":100,"z":100,"w":9,"x":true,"A":255,"B":255,"C":255,"D":255,"E":0,"F":0,"G":0,"H":0,"I":false}],"J":[{"K":[{"u":0,"v":-16,"M":16,"N":16,"O":0,"P":0,"Q":32,"R":32,"y":100,"z":100,"w":1,"x":true,"A":255,"B":255,"C":255,"D":255,"E":0,"F":0,"G":0,"H":0,"I":false},{"u":0,"v":-16,"M":16,"N":16,"O":32,"P":0,"Q":32,"R":32,"y":110,"z":110,"w":1,"x":true,"A":255,"B":255,"C":255,"D":255,"E":0,"F":0,"G":0,"H":0,"I":false},{"u":0,"v":-16,"M":16,"N":16,"O":64,"P":0,"Q":32,"R":32,"y":100,"z":100,"w":1,"x":true,"A":255,"B":255,"C":255,"D":255,"E":0,"F":0,"G":0,"H":0,"I":false},{"u":0,"v":-16,"M":16,"N":16,"O":96,"P":0,"Q":32,"R":32,"y":100,"z":100,"w":1,"x":true,"A":255,"B":255,"C":255,"D":255,"E":0,"F":0,"G":0,"H":0,"I":false},{"u":0,"v":-16,"M":16,"N":16,"O":128,"P":0,"Q":32,"R":32,"y":100,"z":100,"w":1,"x":true,"A":255,"B":255,"C":255,"D":255,"E":0,"F":0,"G":0,"H":0,"I":false},{"u":0,"v":-16,"M":16,"N":16,"O":160,"P":0,"Q":32,"R":32,"y":100,"z":100,"w":1,"x":true,"A":255,"B":255,"C":255,"D":255,"E":0,"F":0,"G":0,"H":0,"I":false},{"u":0,"v":-16,"M":16,"N":16,"O":192,"P":0,"Q":32,"R":32,"y":100,"z":100,"w":1,"x":true,"A":255,"B":255,"C":255,"D":255,"E":0,"F":0,"G":0,"H":0,"I":false},{"u":0,"v":-16,"M":16,"N":16,"O":224,"P":0,"Q":32,"R":32,"y":100,"z":100,"w":1,"x":true,"A":255,"B":255,"C":255,"D":255,"E":0,"F":0,"G":0,"H":0,"I":false},{"u":0,"v":-16,"M":16,"N":16,"O":224,"P":0,"Q":32,"R":32,"y":100,"z":100,"w":1,"x":false,"A":255,"B":255,"C":255,"D":255,"E":0,"F":0,"G":0,"H":0,"I":false}],"L":0,"x":true}],"S":[],"U":[]}]}}