{"a":{"b":"Unknown","c":"9/29/2015 5:38:21 PM","e":"3","d":30},"f":{"g":[{"h":0,"i":"resources/gfx/effects/effect_impact.png"}],"j":[{"h":0,"k":"Main","l":0}],"m":[],"n":[]},"o":{"p":"Main","q":[{"k":"Main","r":6,"s":false,"t":[{"u":0,"v":0,"y":100,"z":100,"w":6,"x":true,"A":255,"B":255,"C":255,"D":255,"E":0,"F":0,"G":0,"H":0,"I":false}],"J":[{"K":[{"u":0,"v":0,"M":32,"N":32,"O":128,"P":64,"Q":64,"R":64,"y":100,"z":100,"w":1,"x":true,"A":255,"B":255,"C":255,"D":255,"E":0,"F":0,"G":0,"H":0,"I":false},{"u":0,"v":0,"M":32,"N":32,"O":192,"P":64,"Q":64,"R":64,"y":100,"z":100,"w":1,"x":true,"A":255,"B":255,"C":255,"D":200,"E":0,"F":0,"G":0,"H":0,"I":false},{"u":0,"v":0,"M":32,"N":32,"O":0,"P":128,"Q":64,"R":64,"y":100,"z":100,"w":1,"x":true,"A":255,"B":255,"C":255,"D":150,"E":0,"F":0,"G":0,"H":0,"I":false},{"u":0,"v":0,"M":32,"N":32,"O":64,"P":128,"Q":64,"R":64,"y":100,"z":100,"w":1,"x":true,"A":255,"B":255,"C":255,"D":100,"E":0,"F":0,"G":0,"H":0,"I":false},{"u":0,"v":0,"M":32,"N":32,"O":128,"P":128,"Q":64,"R":64,"y":100,"z":100,"w":1,"x":true,"A":255,"B":255,"C":255,"D":50,"E":0,"F":0,"G":0,"H":0,"I":false},{"u":0,"v":0,"M":32,"N":32,"O":192,"P":128,"Q":64,"R":64,"y":100,"z":100,"w":1,"x":true,"A":255,"B":255,"C":255,"D":25,"E":0,"F":0,"G":0,"H":0,"I":false}],"L":0,"x":true}],"S":[],"U":[]},{"k":"Blue","r":6,"s":false,"t":[{"u":0,"v":0,"y":100,"z":100,"w":6,"x":true,"A":255,"B":255,"C":255,"D":255,"E":0,"F":0,"G":0,"H":0,"I":false}],"J":[{"K":[{"u":0,"v":0,"M":32,"N":32,"O":0,"P":0,"Q":64,"R":64,"y":100,"z":100,"w":1,"x":true,"A":255,"B":255,"C":255,"D":255,"E":0,"F":0,"G":0,"H":0,"I":false},{"u":0,"v":0,"M":32,"N":32,"O":64,"P":0,"Q":64,"R":64,"y":100,"z":100,"w":1,"x":true,"A":255,"B":255,"C":255,"D":200,"E":0,"F":0,"G":0,"H":0,"I":false},{"u":0,"v":0,"M":32,"N":32,"O":128,"P":0,"Q":64,"R":64,"y":100,"z":100,"w":1,"x":true,"A":255,"B":255,"C":255,"D":150,"E":0,"F":0,"G":0,"H":0,"I":false},{"u":0,"v":0,"M":32,"N":32,"O":192,"P":0,"Q":64,"R":64,"y":100,"z":100,"w":1,"x":true,"A":255,"B":255,"C":255,"D":100,"E":0,"F":0,"G":0,"H":0,"I":false},{"u":0,"v":0,"M":32,"N":32,"O":0,"P":64,"Q":64,"R":64,"y":100,"z":100,"w":1,"x":true,"A":255,"B":255,"C":255,"D":50,"E":0,"F":0,"G":0,"H":0,"I":false},{"u":0,"v":0,"M":32,"N":32,"O":64,"P":64,"Q":64,"R":64,"y":100,"z":100,"w":1,"x":true,"A":255,"B":255,"C":255,"D":25,"E":0,"F":0,"G":0,"H":0,"I":false}],"L":0,"x":true}],"S":[],"U":[]},{"k":"Red","r":6,"s":false,"t":[{"u":0,"v":0,"y":100,"z":100,"w":6,"x":true,"A":255,"B":255,"C":255,"D":255,"E":0,"F":0,"G":0,"H":0,"I":false}],"J":[{"K":[{"u":0,"v":0,"M":32,"N":32,"O":128,"P":64,"Q":64,"R":64,"y":100,"z":100,"w":1,"x":true,"A":255,"B":255,"C":255,"D":255,"E":255,"F":0,"G":0,"H":0,"I":false},{"u":0,"v":0,"M":32,"N":32,"O":192,"P":64,"Q":64,"R":64,"y":100,"z":100,"w":1,"x":true,"A":255,"B":255,"C":255,"D":200,"E":255,"F":0,"G":0,"H":0,"I":false},{"u":0,"v":0,"M":32,"N":32,"O":0,"P":128,"Q":64,"R":64,"y":100,"z":100,"w":1,"x":true,"A":255,"B":255,"C":255,"D":150,"E":255,"F":0,"G":0,"H":0,"I":false},{"u":0,"v":0,"M":32,"N":32,"O":64,"P":128,"Q":64,"R":64,"y":100,"z":100,"w":1,"x":true,"A":255,"B":255,"C":255,"D":100,"E":255,"F":0,"G":0,"H":0,"I":false},{"u":0,"v":0,"M":32,"N":32,"O":128,"P":128,"Q":64,"R":64,"y":100,"z":100,"w":1,"x":true,"A":255,"B":255,"C":255,"D":50,"E":255,"F":0,"G":0,"H":0,"I":false},{"u":0,"v":0,"M":32,"N":32,"O":192,"P":128,"Q":64,"R":64,"y":100,"z":100,"w":1,"x":true,"A":255,"B":255,"C":255,"D":25,"E":255,"F":0,"G":0,"H":0,"I":false}],"L":0,"x":true}],"S":[],"U":[]},{"k":"Yellow","r":6,"s":false,"t":[{"u":0,"v":0,"y":100,"z":100,"w":6,"x":true,"A":255,"B":255,"C":255,"D":255,"E":0,"F":0,"G":0,"H":0,"I":false}],"J":[{"K":[{"u":0,"v":0,"M":32,"N":32,"O":128,"P":64,"Q":64,"R":64,"y":100,"z":100,"w":1,"x":true,"A":255,"B":255,"C":255,"D":255,"E":255,"F":255,"G":0,"H":0,"I":false},{"u":0,"v":0,"M":32,"N":32,"O":192,"P":64,"Q":64,"R":64,"y":100,"z":100,"w":1,"x":true,"A":255,"B":255,"C":255,"D":200,"E":255,"F":255,"G":0,"H":0,"I":false},{"u":0,"v":0,"M":32,"N":32,"O":0,"P":128,"Q":64,"R":64,"y":100,"z":100,"w":1,"x":true,"A":255,"B":255,"C":255,"D":150,"E":255,"F":255,"G":0,"H":0,"I":false},{"u":0,"v":0,"M":32,"N":32,"O":64,"P":128,"Q":64,"R":64,"y":100,"z":100,"w":1,"x":true,"A":255,"B":255,"C":255,"D":100,"E":255,"F":255,"G":0,"H":0,"I":false},{"u":0,"v":0,"M":32,"N":32,"O":128,"P":128,"Q":64,"R":64,"y":100,"z":100,"w":1,"x":true,"A":255,"B":255,"C":255,"D":50,"E":255,"F":255,"G":0,"H":0,"I":false},{"u":0,"v":0,"M":32,"N":32,"O":192,"P":128,"Q":64,"R":64,"y":100,"z":100,"w":1,"x":true,"A":255,"B":255,"C":255,"D":25,"E":255,"F":255,"G":0,"H":0,"I":false}],"L":0,"x":true}],"S":[],"U":[]}]}}