{"a":{"b":"robot","c":"16.07.2015 02:27:22","e":"111","d":30},"f":{"g":[{"h":0,"i":"resources/gfx/grid/door_08_holeinwall_darkroom.png"}],"j":[{"h":0,"k":"body","l":0}],"m":[],"n":[]},"o":{"p":"Close","q":[{"k":"Open","r":32,"s":false,"t":[{"u":0,"v":0,"y":100,"z":100,"w":32,"x":true,"A":255,"B":255,"C":255,"D":255,"E":0,"F":0,"G":0,"H":0,"I":false}],"J":[{"K":[{"u":0,"v":8,"M":32,"N":32,"O":0,"P":0,"Q":64,"R":64,"y":50,"z":50,"w":31,"x":true,"A":255,"B":255,"C":255,"D":0,"E":0,"F":0,"G":0,"H":0,"I":true},{"u":0,"v":8,"M":32,"N":32,"O":0,"P":0,"Q":64,"R":64,"y":100,"z":100,"w":1,"x":true,"A":255,"B":255,"C":255,"D":255,"E":0,"F":0,"G":0,"H":0,"I":false}],"L":0,"x":true}],"S":[],"U":[]},{"k":"Close","r":32,"s":false,"t":[{"u":0,"v":0,"y":100,"z":100,"w":32,"x":true,"A":255,"B":255,"C":255,"D":255,"E":0,"F":0,"G":0,"H":0,"I":false}],"J":[{"K":[{"u":0,"v":8,"M":32,"N":32,"O":0,"P":0,"Q":64,"R":64,"y":100,"z":100,"w":31,"x":true,"A":255,"B":255,"C":255,"D":255,"E":0,"F":0,"G":0,"H":0,"I":true},{"u":0,"v":8,"M":32,"N":32,"O":0,"P":0,"Q":64,"R":64,"y":50,"z":50,"w":1,"x":true,"A":255,"B":255,"C":255,"D":0,"E":0,"F":0,"G":0,"H":0,"I":false}],"L":0,"x":true}],"S":[],"U":[]},{"k":"Hidden","r":1,"s":false,"t":[{"u":0,"v":0,"y":100,"z":100,"w":1,"x":true,"A":255,"B":255,"C":255,"D":255,"E":0,"F":0,"G":0,"H":0,"I":false}],"J":[{"K":[{"u":0,"v":8,"M":32,"N":32,"O":0,"P":0,"Q":64,"R":64,"y":100,"z":100,"w":1,"x":false,"A":255,"B":255,"C":255,"D":255,"E":0,"F":0,"G":0,"H":0,"I":false}],"L":0,"x":true}],"S":[],"U":[]},{"k":"Opened","r":13,"s":true,"t":[{"u":0,"v":0,"y":100,"z":100,"w":2,"x":true,"A":255,"B":255,"C":255,"D":255,"E":0,"F":0,"G":0,"H":0,"I":false}],"J":[{"K":[{"u":0,"v":8,"M":32,"N":32,"O":0,"P":0,"Q":64,"R":64,"y":100,"z":100,"w":4,"x":true,"A":255,"B":255,"C":255,"D":255,"E":0,"F":0,"G":0,"H":0,"I":true},{"u":0,"v":8,"M":32,"N":32,"O":0,"P":0,"Q":64,"R":64,"y":105,"z":95,"w":4,"x":true,"A":255,"B":255,"C":255,"D":255,"E":0,"F":0,"G":0,"H":0,"I":true},{"u":0,"v":8,"M":32,"N":32,"O":0,"P":0,"Q":64,"R":64,"y":100,"z":100,"w":4,"x":true,"A":255,"B":255,"C":255,"D":255,"E":0,"F":0,"G":0,"H":0,"I":true},{"u":0,"v":8,"M":32,"N":32,"O":0,"P":0,"Q":64,"R":64,"y":95,"z":105,"w":1,"x":true,"A":255,"B":255,"C":255,"D":255,"E":0,"F":0,"G":0,"H":0,"I":true}],"L":0,"x":true}],"S":[],"U":[]}]}}